<?xml version="1.0" encoding="UTF-8"?>
<OpenSearchDescription xmlns="http://a9.com/-/spec/opensearch/1.1/" xmlns:moz="http://www.mozilla.org/2006/browser/search/">
      <ShortName>fjump</ShortName>
      <Description>Quikly navigate the web</Description>
      <InputEncoding>UTF-8</InputEncoding>
      <OutputEncoding>UTF-8</OutputEncoding>
      <Language>en-us</Language>
      <Image width="32" height="32" type="image/png">https://fjump.to/favicon.png</Image>
      <Tags>fjump</Tags>
      <Url type="text/html" template="https://fjump.to/?q={searchTerms}" />
      <moz:SearchForm>https://fjump.to/?q=</moz:SearchForm>
</OpenSearchDescription>
